{
  "ssdb": true,
  "idstr": "4046342202260698",
  "mid": "4046342202260698",
  "user": {
    "screen_name": "SNH48-王晓佳应援会",
    "location": "上海 黄浦区",
    "description": "",
    "followers_count": "1639",
    "friends_count": "4",
    "statuses_count": "33",
    "favourites_count": "0",
    "created_at": "Thu Dec 18 10:50:17 +0800 2014",
    "verified_reason": "＃王晓佳＃超级话题主持人团队",
    "profile_image_url": "http://tvax4.sinaimg.cn/crop.0.0.996.996.180/005Vv4awly8fj7knfkv10j30ro0rodib.jpg",
    "cover_image_phone": "http://wx3.sinaimg.cn/crop.0.0.640.640.640/005ZysU6gy1fe94jymgztj30ku0kuq3z.jpg",
    "cover_image": "",
    "updated_at": "1504855097",
    "gender": "f",
    "bi_followers_count": "3",
    "id": "5430319508",
    "idstr": "5430319508",
    "uid": "5430319508",
    "ssdb_count": 2223,
    "delete": null
  },
  "created_at": "2016-11-27 08:30:21",
  "text": "[爱你]谢谢返图～#SNH48王晓佳#",
  "source": "手癌王のAndroid",
  "reposts_count": "2",
  "comments_count": "0",
  "attitudes_count": "14",
  "rt_uid": "5235077242",
  "rt_id": "4046234505841969",
  "retweeted_status": {
    "ssdb": true,
    "idstr": "4046234505841969",
    "mid": "4046234505841969",
    "user": {
      "screen_name": "老伺机Kz",
      "location": "山东 淄博",
      "description": "宇宙最稳 单推你河",
      "followers_count": "272",
      "friends_count": "782",
      "statuses_count": "835",
      "favourites_count": "2",
      "created_at": "Mon Jul 28 23:35:26 +0800 2014",
      "verified_reason": "",
      "profile_image_url": "http://tvax2.sinaimg.cn/crop.0.0.996.996.180/005IhQJIly8fgyxx4alqwj30ro0ro40k.jpg",
      "cover_image_phone": "http://ww2.sinaimg.cn/crop.0.0.640.640.640/6ab6b999gw1f9ijl3cwozj20ku0ks74i.jpg",
      "cover_image": "http://ww2.sinaimg.cn/crop.0.0.920.300/005IhQJIgw1fa89uepkymj30pk08c416.jpg",
      "updated_at": "1500656874",
      "gender": "m",
      "bi_followers_count": "175",
      "id": "5235077242",
      "idstr": "5235077242",
      "uid": "5235077242",
      "ssdb_count": 265,
      "delete": null
    },
    "created_at": "2016-11-27 01:22:24",
    "text": "#SNH48王晓佳# 20161126黄花机场送机 你草真的real累 没拍出很好看的图片很可惜 要好好休息 真的real可爱@SNH48-王晓佳 @SNH48-王晓佳应援会 ​",
    "source": "微博 weibo.com",
    "reposts_count": "3",
    "comments_count": "3",
    "attitudes_count": "7",
    "rt_uid": "0",
    "rt_id": "0",
    "pic_urls": [
      "http://ww2.sinaimg.cn/thumbnail/005IhQJIgw1fa60o8vor1j311x1kwn62.jpg",
      "http://ww3.sinaimg.cn/thumbnail/005IhQJIgw1fa60oduoaoj31kw11x498.jpg",
      "http://ww2.sinaimg.cn/thumbnail/005IhQJIgw1fa60ohymw5j31kw11xn6w.jpg",
      "http://ww4.sinaimg.cn/thumbnail/005IhQJIgw1fa60onondij31kw11xakq.jpg"
    ]
  }
}