{
  "ssdb": true,
  "idstr": "4050795739894936",
  "mid": "4050795739894936",
  "user": {
    "screen_name": "SNH48-王晓佳应援会",
    "location": "上海 黄浦区",
    "description": "",
    "followers_count": "1639",
    "friends_count": "4",
    "statuses_count": "33",
    "favourites_count": "0",
    "created_at": "Thu Dec 18 10:50:17 +0800 2014",
    "verified_reason": "＃王晓佳＃超级话题主持人团队",
    "profile_image_url": "http://tvax4.sinaimg.cn/crop.0.0.996.996.180/005Vv4awly8fj7knfkv10j30ro0rodib.jpg",
    "cover_image_phone": "http://wx3.sinaimg.cn/crop.0.0.640.640.640/005ZysU6gy1fe94jymgztj30ku0kuq3z.jpg",
    "cover_image": "",
    "updated_at": "1504855097",
    "gender": "f",
    "bi_followers_count": "3",
    "id": "5430319508",
    "idstr": "5430319508",
    "uid": "5430319508",
    "ssdb_count": 2223,
    "delete": null
  },
  "created_at": "2016-12-09 15:27:06",
  "text": "#一起为所欲为#@SNH48-王晓佳 @穿越火线 [哈哈][哈哈][哈哈][哈哈]记得来看我们的草草哦[爱你]",
  "source": "美图M6•自拍大明星",
  "reposts_count": "4",
  "comments_count": "1",
  "attitudes_count": "5",
  "rt_uid": "5669287577",
  "rt_id": "4050745252900075",
  "retweeted_status": {
    "ssdb": true,
    "idstr": "4050745252900075",
    "mid": "4050745252900075",
    "user": {
      "screen_name": "穿越火线",
      "location": "其他",
      "description": "穿越火线官方微博",
      "followers_count": "196615",
      "friends_count": "282",
      "statuses_count": "1486",
      "favourites_count": "1",
      "created_at": "Wed Aug 05 15:19:07 +0800 2015",
      "verified_reason": "穿越火线官方微博",
      "profile_image_url": "http://tvax4.sinaimg.cn/crop.91.21.315.315.180/006bFKGdly8fgkvu0acvwj30dh0cy120.jpg",
      "cover_image_phone": "http://ww1.sinaimg.cn/crop.0.0.640.640.640/549d0121tw1egm1kjly3jj20hs0hsq4f.jpg",
      "cover_image": "http://wx4.sinaimg.cn/crop.0.0.920.300/006bFKGdgy1fg05fq2h5hj30pk08c7hw.jpg",
      "updated_at": "1505381036",
      "gender": "m",
      "bi_followers_count": "149",
      "id": "5669287577",
      "idstr": "5669287577",
      "uid": "5669287577",
      "ssdb_count": 1202,
      "delete": null
    },
    "created_at": "2016-12-09 12:06:30",
    "text": "#一起为所欲为# 厉害了word CF手游周年庆！ 各路明星发来贺电，#黄子韬# ，#关爱八卦成长协会# ，#袁成杰#，#SNH48# ，#GNZ48#，还有好莱坞大师音乐大师泰勒·贝兹都来啦~亲爱的你们怎么能不来呢！12月9-10日，CF手游周年庆生日趴，火线姐等你来！周年庆收看链接：http://t.cn/RI7MT3L （PC版），  ​",
    "source": "微博 weibo.com",
    "reposts_count": "1284",
    "comments_count": "264",
    "attitudes_count": "233",
    "rt_uid": "0",
    "rt_id": "0"
  }
}