{
  "ssdb": true,
  "idstr": "4136311344678033",
  "mid": "4136311344678033",
  "user": {
    "screen_name": "SNH48-王晓佳应援会",
    "location": "上海 黄浦区",
    "description": "",
    "followers_count": "1639",
    "friends_count": "4",
    "statuses_count": "33",
    "favourites_count": "0",
    "created_at": "Thu Dec 18 10:50:17 +0800 2014",
    "verified_reason": "＃王晓佳＃超级话题主持人团队",
    "profile_image_url": "http://tvax4.sinaimg.cn/crop.0.0.996.996.180/005Vv4awly8fj7knfkv10j30ro0rodib.jpg",
    "cover_image_phone": "http://wx3.sinaimg.cn/crop.0.0.640.640.640/005ZysU6gy1fe94jymgztj30ku0kuq3z.jpg",
    "cover_image": "",
    "updated_at": "1504855097",
    "gender": "f",
    "bi_followers_count": "3",
    "id": "5430319508",
    "idstr": "5430319508",
    "uid": "5430319508",
    "ssdb_count": 2223,
    "delete": null
  },
  "created_at": "2017-08-02 14:55:36",
  "text": "#王晓佳# \n\n20170801   口袋48房间翻牌Part2\n\n房间名字和介绍更新了哦：天草的秘密会谈室。\n如果大家有想问天草的问题，可以在房间留言，也许会有随缘翻牌[偷笑]\n\n让我们一起陪伴这个暖心小偶像吧w ​",
  "source": "iPhone 6",
  "reposts_count": "0",
  "comments_count": "0",
  "attitudes_count": "11",
  "rt_uid": "0",
  "rt_id": "0",
  "pic_urls": [
    "http://wx1.sinaimg.cn/thumbnail/005Vv4awgy1fi5dv4tyfbj30hs635wzp.jpg",
    "http://wx3.sinaimg.cn/thumbnail/005Vv4awgy1fi5dv6uskfj30hs60fe17.jpg",
    "http://wx3.sinaimg.cn/thumbnail/005Vv4awgy1fi5dv8k07dj30hs5r1ttc.jpg",
    "http://wx2.sinaimg.cn/thumbnail/005Vv4awgy1fi5dvae4bxj30hs63fawq.jpg",
    "http://wx4.sinaimg.cn/thumbnail/005Vv4awgy1fi5dvc4ztxj30hs6621dr.jpg",
    "http://wx4.sinaimg.cn/thumbnail/005Vv4awgy1fi5dvdw3f0j30hs4454d3.jpg",
    "http://wx1.sinaimg.cn/thumbnail/005Vv4awgy1fi5dveopflj30ku112dj1.jpg"
  ]
}